SKHASH/SKHASH.py
SKHASH/__init__.py
SKHASH/functions/__init__.py
SKHASH/functions/compute_mech.py
SKHASH/functions/fun.py
SKHASH/functions/gridsearch.f
SKHASH/functions/gridsearch_so.py
SKHASH/functions/in_other.py
SKHASH/functions/in_pol.py
SKHASH/functions/in_qc.py
SKHASH/functions/in_sp.py
SKHASH/functions/in_sta.py
SKHASH/functions/out.py
SKHASH/functions/plot_mech.py
skhash-1.1.4.dist-info/METADATA
skhash-1.1.4.dist-info/WHEEL
skhash-1.1.4.dist-info/entry_points.txt
skhash-1.1.4.dist-info/licenses/LICENSE.md
skhash-1.1.4.dist-info/RECORD
