Metadata-Version: 2.4
Name: SKHASH
Version: 1.1.4
Summary: Python package for earthquake focal mechanism inversions
Project-URL: Homepage, https://code.usgs.gov/esc/SKHASH
Project-URL: Issues, https://code.usgs.gov/esc/SKHASH/-/issues
Author-email: "Robert J. Skoumal" <rskoumal@usgs.gov>
License-Expression: CC0-1.0
License-File: LICENSE.md
Classifier: Operating System :: OS Independent
Classifier: Programming Language :: Python :: 3
Requires-Python: >=3.8
Requires-Dist: meson; python_version >= '3.12'
Requires-Dist: ninja; python_version >= '3.12'
Requires-Dist: numpy<2.0
Requires-Dist: pandas
Provides-Extra: plot
Requires-Dist: matplotlib; extra == 'plot'
